rtl/data_mem.v
/*
 * Copyright (c) 2026 Zhiyuan (Jerry) Jiang
 * SPDX-License-Identifier: Apache-2.0
 */

`default_nettype none


 module data_mem (
    input wire clk,
    input wire mem_write,
    input wire mem_read,
    input wire [31:0] address,
    input wire [31:0] write_data,
    output wire [31:0] read_data
 );

reg [31:0] mem_array [0:1023];

always @(posedge clk) begin

    if (mem_write) begin
        mem_array[address[31:2]] <= write_data;

    end
end

assign read_data = (mem_read) ? mem_array[address[31:2]] : 32'b0;

 endmodule

tb/modules/tb_data_mem.sv
/*
 * Copyright (c) 2026 Zhiyuan (Jerry) Jiang
 * SPDX-License-Identifier: Apache-2.0
 *
 *
 * cd into sim first, then run wsl, then run the following:
 * "iverilog -g2012 -o data_mem_test ../tb/modules/tb_data_mem.sv ../rtl/data_mem.v"
 * Then: "vvp data_mem_test"
 * Then: "gtkwave tb_data_mem.vcd tb_data_mem.gtkw" to view waveform
 */


`default_nettype none
`timescale 1ns/1ps


module tb_data_mem;

    logic clk;
    logic mem_write;
    logic mem_read;
    logic [31:0] address;
    logic [31:0] write_data;
    
    logic [31:0] read_data;


    data_mem dut (
        .clk(clk),
        .mem_write(mem_write),
        .mem_read(mem_read),
        .address(address),
        .write_data(write_data),
        .read_data(read_data)
    );


    //clk
    initial clk = 0;
    always #5 clk = ~clk; 


    initial begin

        //output files setup
        $dumpfile("tb_data_mem.vcd");
        $dumpvars(0, tb_data_mem);


        //clearing chip signals
        mem_write = 1'b0;
        mem_read = 1'b0;
        address = 32'd0;
        write_data = 32'd0;
        #20; 


        $display("Starting Data Memory tests...");


        //test 1 basic write and read
        $display("Test 1: Basic Write and Read (Address 4)");
        address = 32'd4;
        write_data = 32'hDEADBEEF;
        mem_write = 1'b1;
        
        @(posedge clk);
        #1;
        mem_write = 1'b0;

        address = 32'd4;
        mem_read = 1'b1;
        #1;

        assert (read_data == 32'hDEADBEEF) begin
            $display("Test 1 passed");
        end 
        else begin
            $fatal(1, "Error: Write/Read failed. Expected DEADBEEF, got %h", read_data);
        end


        //test 2 mem_read disable test
        $display("Test 2: Memory Read Disable");
        mem_read = 1'b0;
        #1;

        assert (read_data == 32'h00000000) begin
            $display("Test 2 passed");
        end 
        else begin
            $fatal(1, "Error: mem_read disable failed. Expected 00000000, got %h", read_data);
        end


        //test 3 write isolation check
        $display("Test 3: Write Isolation Check (Address 8 vs 4)");
        //write to address 8
        address = 32'd8;
        write_data = 32'hDAD69420;
        mem_write = 1'b1;
        
        @(posedge clk);
        #1;
        mem_write = 1'b0;

        //read back address 4 to ensure it wasn't overwritten
        address = 32'd4;
        mem_read = 1'b1;
        #1;

        assert (read_data == 32'hDEADBEEF) begin
            $display("Test 3 passed");
        end 
        else begin
            $fatal(1, "Error: Memory corrupted! Address 4 was overwritten. Got %h", read_data);
        end


        //test 4 word alignment check [31:2]
        $display("Test 4: Word Alignment Check");
        //write to address 12
        address = 32'd12;
        write_data = 32'h12345678;
        mem_write = 1'b1;
        mem_read = 1'b0;
        
        @(posedge clk);
        #1;
        mem_write = 1'b0;

        //try reading from address 15 (should map to the exact same word as 12)
        address = 32'd15;
        mem_read = 1'b1;
        #1;

        assert (read_data == 32'h12345678) begin
            $display("Test 4 passed");
        end 
        else begin
            $fatal(1, "Error: Word alignment [31:2] failed. Expected 12345678, got %h", read_data);
        end


        $display("All Data Memory tests successful, use 'gtkwave tb_data_mem.vcd tb_data_mem.gtkw' to open waveform.");
        
        $finish;

    end

endmodule

sim/tb_data_mem.vcd
$date
	Thu Jul 16 03:32:15 2026
$end
$version
	Icarus Verilog
$end
$timescale
	1ps
$end
$scope module tb_data_mem $end
$var wire 32 ! read_data [31:0] $end
$var reg 32 " address [31:0] $end
$var reg 1 # clk $end
$var reg 1 $ mem_read $end
$var reg 1 % mem_write $end
$var reg 32 & write_data [31:0] $end
$scope module dut $end
$var wire 32 ' address [31:0] $end
$var wire 1 # clk $end
$var wire 1 $ mem_read $end
$var wire 1 % mem_write $end
$var wire 32 ( write_data [31:0] $end
$var wire 32 ) read_data [31:0] $end
$upscope $end
$upscope $end
$enddefinitions $end
$comment Show the parameter values. $end
$dumpall
$end
#0
$dumpvars
b0 )
b0 (
b0 '
b0 &
0%
0$
0#
b0 "
b0 !
$end
#5000
1#
#10000
0#
#15000
1#
#20000
0#
1%
b11011110101011011011111011101111 &
b11011110101011011011111011101111 (
b100 "
b100 '
#25000
1#
#26000
b11011110101011011011111011101111 !
b11011110101011011011111011101111 )
1$
0%
#27000
b0 !
b0 )
0$
#28000
1%
b11011010110101101001010000100000 &
b11011010110101101001010000100000 (
b1000 "
b1000 '
#30000
0#
#35000
1#
#36000
b11011110101011011011111011101111 !
b11011110101011011011111011101111 )
1$
b100 "
b100 '
0%
#37000
b0 !
b0 )
0$
1%
b10010001101000101011001111000 &
b10010001101000101011001111000 (
b1100 "
b1100 '
#40000
0#
#45000
1#
#46000
b10010001101000101011001111000 !
b10010001101000101011001111000 )
1$
b1111 "
b1111 '
0%
