rtl/store_mask.v
/*
 * Copyright (c) 2026 Zhiyuan (Jerry) Jiang
 * SPDX-License-Identifier: Apache-2.0
 */

`default_nettype none


 module store_mask (
    input wire [2:0] func3,
    input wire [1:0] byte_offset,
    input wire [31:0] rs2_data,
    output reg [3:0] write_mask,
    output reg [31:0] store_data
 );

 reg [31:0] shifted_data;

 always @(*) begin

    
    shifted_data = rs2_data << (byte_offset * 8);
    
    case(func3)

    3'b010: begin //sw
        write_mask = 4'b1111;
        store_data = rs2_data;
    end

    3'b000: begin //sb
        write_mask = 4'b0001 << byte_offset;
        store_data = shifted_data;
    end

    3'b001: begin //sh

        if (byte_offset == 2'd2 || byte_offset == 2'd0) begin // making sure no misaligned half words >:)
            write_mask = 4'b0011 << byte_offset;
            store_data = shifted_data;
        end

        else begin
            write_mask = 4'b0000;
            store_data = 32'b0;
        end
    end

    default: begin
        write_mask = 4'b0000;
        store_data = 32'b0;
    end

    endcase

 end



 endmodule

tb/modules/tb_store_mask.sv
/*
 * Copyright (c) 2026 Zhiyuan (Jerry) Jiang
 * SPDX-License-Identifier: Apache-2.0
 *
 * cd into sim first, then run wsl, then run the following:
 * "iverilog -g2012 -o store_mask_test ../tb/modules/tb_store_mask.sv ../rtl/store_mask.v"
 * Then: "vvp store_mask_test"
 * Then: "gtkwave tb_store_mask.vcd tb_store_mask.gtkw" to view waveform
 */

`default_nettype none
`timescale 1ns/1ps

module tb_store_mask;

    logic [31:0] write_data_in;
    logic [2:0] func3;
    logic [1:0] byte_offset;

    logic [31:0] masked_data_out;
    logic [3:0] write_mask_out;

    store_mask dut (
        .rs2_data(write_data_in),
        .func3(func3),
        .byte_offset(byte_offset),
        .store_data(masked_data_out),
        .write_mask(write_mask_out)
    );

    initial begin
        // output files setup
        $dumpfile("tb_store_mask.vcd");
        $dumpvars(0, tb_store_mask);

        // clearing chip signals
        write_data_in = 32'd0;
        func3 = 3'd0;
        byte_offset = 2'd0;
        #20;

        $display("Starting Store Mask tests...");

        // test 1: sw
        $display("Test 1: Store Word (SW)");
        func3 = 3'b010;
        byte_offset = 2'b00;
        write_data_in = 32'hDEADBEEF;
        #10;
        assert(write_mask_out == 4'b1111 && masked_data_out == 32'hDEADBEEF) begin
            $display("Test 1 passed");
        end else begin
            $fatal(1, "Error: SW failed. Expected Mask: 1111, Data: DEADBEEF. Got Mask: %b, Data: %h", write_mask_out, masked_data_out);
        end

        // test 2: sh offset 0
        $display("Test 2: Store Halfword (SH) Offset 0");
        func3 = 3'b001;
        byte_offset = 2'b00;
        write_data_in = 32'h0000BEEF;
        #10;
        assert(write_mask_out == 4'b0011 && masked_data_out[15:0] == 16'hBEEF) begin
            $display("Test 2 passed");
        end else begin
            $fatal(1, "Error: SH Offset 0 failed. Expected Mask: 0011, Data[15:0]: BEEF. Got Mask: %b, Data: %h", write_mask_out, masked_data_out);
        end

        // test 3: sh offset 2
        $display("Test 3: Store Halfword (SH) Offset 2");
        func3 = 3'b001;
        byte_offset = 2'b10;
        write_data_in = 32'h0000BEEF; 
        #10;
        assert(write_mask_out == 4'b1100 && masked_data_out[31:16] == 16'hBEEF) begin
            $display("Test 3 passed");
        end else begin
            $fatal(1, "Error: SH Offset 2 failed. Expected Mask: 1100, Data[31:16]: BEEF. Got Mask: %b, Data: %h", write_mask_out, masked_data_out);
        end

        // test 4: sb offset 0
        $display("Test 4: Store Byte (SB) Offset 0");
        func3 = 3'b000;
        byte_offset = 2'b00;
        write_data_in = 32'h000000AA; 
        #10;
        assert(write_mask_out == 4'b0001 && masked_data_out[7:0] == 8'hAA) begin
            $display("Test 4 passed");
        end else begin
            $fatal(1, "Error: SB Offset 0 failed. Expected Mask: 0001, Data[7:0]: AA. Got Mask: %b, Data: %h", write_mask_out, masked_data_out);
        end

        // test 5: sb offset 1
        $display("Test 5: Store Byte (SB) Offset 1");
        func3 = 3'b000;
        byte_offset = 2'b01;
        write_data_in = 32'h000000BB; 
        #10;
        assert(write_mask_out == 4'b0010 && masked_data_out[15:8] == 8'hBB) begin
            $display("Test 5 passed");
        end else begin
            $fatal(1, "Error: SB Offset 1 failed. Expected Mask: 0010, Data[15:8]: BB. Got Mask: %b, Data: %h", write_mask_out, masked_data_out);
        end

        // test 6: sb offset 3
        $display("Test 6: Store Byte (SB) Offset 3");
        func3 = 3'b000;
        byte_offset = 2'b11;
        write_data_in = 32'h000000CC; 
        #10;
        assert(write_mask_out == 4'b1000 && masked_data_out[31:24] == 8'hCC) begin
            $display("Test 6 passed");
        end else begin
            $fatal(1, "Error: SB Offset 3 failed. Expected Mask: 1000, Data[31:24]: CC. Got Mask: %b, Data: %h", write_mask_out, masked_data_out);
        end
        

        // test 7: invalid func3
        $display("Test 6: Invalid func3");
        func3 = 3'b111;
        byte_offset = 2'b01;
        write_data_in = 32'h000000CC; 
        #10;
        assert(write_mask_out == 4'b0000 && masked_data_out == 32'b0) begin
            $display("Test 7 passed");
        end else begin
            $fatal(1, "Error: Invalid func3 failed. Expected Mask: 0000, Data: 0x00000000. Got Mask: %b, Data: %h", write_mask_out, masked_data_out);
        end

        // test 8: invalid half word alignment
        $display("Test 6: Invalid Half Word Alignment");
        func3 = 3'b001;
        byte_offset = 2'b01;
        write_data_in = 32'h0000DEAD; 
        #10;
        assert(write_mask_out == 4'b0000 && masked_data_out == 32'b0) begin
            $display("Test 8 passed");
        end else begin
            $fatal(1, "Error: Invalid half word alignment failed. Expected Mask: 0000, Data: 0x00000000. Got Mask: %b, Data: %h", write_mask_out, masked_data_out);
        end


        $display("All Store Mask tests successful, use 'gtkwave tb_store_mask.vcd tb_store_mask.gtkw' to open waveform.");
        


        $finish;

    end

endmodule

sim/tb_store_mask.vcd
$date
	Wed Jul 22 04:10:03 2026
$end
$version
	Icarus Verilog
$end
$timescale
	1ps
$end
$scope module tb_store_mask $end
$var wire 4 ! write_mask_out [3:0] $end
$var wire 32 " masked_data_out [31:0] $end
$var reg 2 # byte_offset [1:0] $end
$var reg 3 $ func3 [2:0] $end
$var reg 32 % write_data_in [31:0] $end
$scope module dut $end
$var wire 2 & byte_offset [1:0] $end
$var wire 3 ' func3 [2:0] $end
$var wire 32 ( rs2_data [31:0] $end
$var reg 32 ) shifted_data [31:0] $end
$var reg 32 * store_data [31:0] $end
$var reg 4 + write_mask [3:0] $end
$upscope $end
$upscope $end
$enddefinitions $end
$comment Show the parameter values. $end
$dumpall
$end
#0
$dumpvars
b1 +
b0 *
b0 )
b0 (
b0 '
b0 &
b0 %
b0 $
b0 #
b0 "
b1 !
$end
#20000
b11011110101011011011111011101111 "
b11011110101011011011111011101111 *
b1111 !
b1111 +
b11011110101011011011111011101111 )
b11011110101011011011111011101111 %
b11011110101011011011111011101111 (
b10 $
b10 '
#30000
b1011111011101111 "
b1011111011101111 *
b11 !
b11 +
b1011111011101111 )
b1011111011101111 %
b1011111011101111 (
b1 $
b1 '
#40000
b10111110111011110000000000000000 "
b10111110111011110000000000000000 *
b1100 !
b1100 +
b10111110111011110000000000000000 )
b10 #
b10 &
#50000
b10101010 "
b10101010 *
b1 !
b1 +
b10101010 )
b10101010 %
b10101010 (
b0 #
b0 &
b0 $
b0 '
#60000
b1011101100000000 "
b1011101100000000 *
b10 !
b10 +
b1011101100000000 )
b10111011 %
b10111011 (
b1 #
b1 &
#70000
b11001100000000000000000000000000 "
b11001100000000000000000000000000 *
b1000 !
b1000 +
b11001100000000000000000000000000 )
b11001100 %
b11001100 (
b11 #
b11 &
#80000
b0 "
b0 *
b0 !
b0 +
b1100110000000000 )
b1 #
b1 &
b111 $
b111 '
#90000
b110111101010110100000000 )
b1101111010101101 %
b1101111010101101 (
b1 $
b1 '
